japan_fiscal_simulator/__init__.py
japan_fiscal_simulator/cli/__init__.py
japan_fiscal_simulator/cli/commands.py
japan_fiscal_simulator/cli/main.py
japan_fiscal_simulator/core/__init__.py
japan_fiscal_simulator/core/derived_coefficients.py
japan_fiscal_simulator/core/equation_system.py
japan_fiscal_simulator/core/linear_solver.py
japan_fiscal_simulator/core/model.py
japan_fiscal_simulator/core/nk_model.py
japan_fiscal_simulator/core/simulation.py
japan_fiscal_simulator/core/solver.py
japan_fiscal_simulator/core/steady_state.py
japan_fiscal_simulator/core/equations/__init__.py
japan_fiscal_simulator/core/equations/base.py
japan_fiscal_simulator/core/equations/fiscal_rule.py
japan_fiscal_simulator/core/equations/is_curve.py
japan_fiscal_simulator/core/equations/phillips_curve.py
japan_fiscal_simulator/core/equations/taylor_rule.py
japan_fiscal_simulator/mcp/__init__.py
japan_fiscal_simulator/mcp/resources.py
japan_fiscal_simulator/mcp/server.py
japan_fiscal_simulator/mcp/tools.py
japan_fiscal_simulator/output/__init__.py
japan_fiscal_simulator/output/graphs.py
japan_fiscal_simulator/output/reports.py
japan_fiscal_simulator/output/schemas.py
japan_fiscal_simulator/parameters/__init__.py
japan_fiscal_simulator/parameters/calibration.py
japan_fiscal_simulator/parameters/constants.py
japan_fiscal_simulator/parameters/defaults.py
japan_fiscal_simulator/policies/__init__.py
japan_fiscal_simulator/policies/consumption_tax.py
japan_fiscal_simulator/policies/social_security.py
japan_fiscal_simulator/policies/subsidies.py
jpfs-0.0.3.dist-info/METADATA
jpfs-0.0.3.dist-info/WHEEL
jpfs-0.0.3.dist-info/entry_points.txt
jpfs-0.0.3.dist-info/RECORD
