Metadata-Version: 2.4
Name: jpfs
Version: 0.0.3
Summary: Japan Fiscal Simulator - New Keynesian DSGEモデルによる財政政策分析
Author: Japan Fiscal Team
License: MIT
Keywords: dsge,economics,fiscal-policy,japan,simulation
Classifier: Development Status :: 3 - Alpha
Classifier: Intended Audience :: Science/Research
Classifier: Programming Language :: Python :: 3.14
Classifier: Topic :: Scientific/Engineering :: Mathematics
Requires-Python: >=3.14
Requires-Dist: jinja2>=3.1.0
Requires-Dist: matplotlib>=3.7.0
Requires-Dist: mcp>=1.0.0
Requires-Dist: numpy>=1.24.0
Requires-Dist: pydantic>=2.0.0
Requires-Dist: rich>=13.0.0
Requires-Dist: scipy>=1.10.0
Requires-Dist: typer>=0.9.0
Provides-Extra: dev
Requires-Dist: mypy>=1.0.0; extra == 'dev'
Requires-Dist: pytest-cov>=4.0.0; extra == 'dev'
Requires-Dist: pytest>=7.0.0; extra == 'dev'
Requires-Dist: ruff>=0.1.0; extra == 'dev'
